reverse_api/__init__.py
reverse_api/action_recorder.py
reverse_api/auto_engineer.py
reverse_api/base_engineer.py
reverse_api/browser.py
reverse_api/cli.py
reverse_api/collector.py
reverse_api/collector_ui.py
reverse_api/config.py
reverse_api/engineer.py
reverse_api/messages.py
reverse_api/native_host.py
reverse_api/opencode_engineer.py
reverse_api/opencode_ui.py
reverse_api/playwright_codegen.py
reverse_api/pricing.py
reverse_api/session.py
reverse_api/sync.py
reverse_api/tui.py
reverse_api/utils.py
reverse_api_engineer-0.3.2.dist-info/METADATA
reverse_api_engineer-0.3.2.dist-info/WHEEL
reverse_api_engineer-0.3.2.dist-info/entry_points.txt
reverse_api_engineer-0.3.2.dist-info/licenses/LICENSE
reverse_api_engineer-0.3.2.dist-info/RECORD
