Metadata-Version: 2.4
Name: reverse-api-engineer
Version: 0.3.2
Summary: A tool to capture browser traffic for API reverse engineering
Project-URL: Homepage, https://github.com/kalil0321/reverse-api-engineer
Project-URL: Repository, https://github.com/kalil0321/reverse-api-engineer
Project-URL: Issues, https://github.com/kalil0321/reverse-api-engineer/issues
Author-email: Kalil <kalil0321@users.noreply.github.com>
License: MIT
License-File: LICENSE
Keywords: api,browser,claude,har,playwright,reverse-engineering
Classifier: Development Status :: 3 - Alpha
Classifier: Intended Audience :: Developers
Classifier: License :: OSI Approved :: MIT License
Classifier: Programming Language :: Python :: 3
Classifier: Programming Language :: Python :: 3.11
Classifier: Programming Language :: Python :: 3.12
Classifier: Programming Language :: Python :: 3.13
Classifier: Topic :: Internet :: WWW/HTTP
Classifier: Topic :: Software Development :: Libraries :: Python Modules
Requires-Python: >=3.11
Requires-Dist: aiohttp>=3.12.15
Requires-Dist: anthropic>=0.40.0
Requires-Dist: brotli>=1.2.0
Requires-Dist: claude-agent-sdk>=0.1.0
Requires-Dist: click>=8.1.0
Requires-Dist: playwright-stealth>=1.0.0
Requires-Dist: playwright>=1.40.0
Requires-Dist: questionary>=2.0.0
Requires-Dist: requests>=2.32.5
Requires-Dist: rich>=13.0.0
Requires-Dist: setproctitle>=1.3.0
Requires-Dist: watchdog>=3.0.0
Provides-Extra: agent
Requires-Dist: stagehand; extra == 'agent'
Provides-Extra: collector
Requires-Dist: beautifulsoup4>=4.12.0; extra == 'collector'
Requires-Dist: markdownify>=0.12.0; extra == 'collector'
Provides-Extra: pricing
Requires-Dist: litellm>=1.0.0; extra == 'pricing'
